wordc/__init__.py
wordc/__main__.py
wordc/cli.py
wordc/config.py
wordc/exceptions.py
wordc/utils.py
wordc/wordc.py
wordc-1.0.1.dist-info/LICENSE
wordc-1.0.1.dist-info/METADATA
wordc-1.0.1.dist-info/WHEEL
wordc-1.0.1.dist-info/entry_points.txt
wordc-1.0.1.dist-info/top_level.txt
wordc-1.0.1.dist-info/RECORD
