Metadata-Version: 2.1
Name: wordc
Version: 1.0.1
Summary: boilerplate you need to create a Python package.
Home-page: https://github.com/Stephen-RA-King/wordc
Download-URL: https://github.com/Stephen-RA-King/wordc/archive/refs/heads/main.zip
Author: Stephen R A King
Author-email: sking.github@gmail.com
Maintainer: Stephen R A King
Maintainer-email: sking.github@gmail.com
License: MIT
Project-URL: Bug Tracker, https://github.com/Stephen-RA-King/wordc/issues
Project-URL: CI, https://github.com/Stephen-RA-King/wordc/actions
Project-URL: Documentation, https://wordc.readthedocs.io/en/latest/
Project-URL: Release Notes, https://github.com/Stephen-RA-King/wordc/releases
Project-URL: Source Code, https://github.com/Stephen-RA-King/wordc/
Keywords: utility
Platform: Any
Classifier: Development Status :: 1 - Planning
Classifier: Environment :: Console
Classifier: Intended Audience :: Developers
Classifier: Operating System :: OS Independent
Classifier: Natural Language :: English
Classifier: Programming Language :: Python :: 3
Classifier: Programming Language :: Python :: 3 :: Only
Classifier: Programming Language :: Python :: 3.8
Classifier: Programming Language :: Python :: 3.9
Classifier: Programming Language :: Python :: 3.10
Classifier: Programming Language :: Python :: 3.11
Classifier: Programming Language :: Python :: 3.12
Requires-Python: >=3.8
License-File: LICENSE
Requires-Dist: chardet >=5.2.0
Requires-Dist: psutil >=5.9.8
